cms/__init__.py
cms/__pycache__/__init__.cpython-35.pyc
cms/accounts/__init__.py
cms/accounts/admin.py
cms/accounts/apps.py
cms/accounts/serializers.py
cms/accounts/social_pipeline.py
cms/accounts/urls.py
cms/accounts/utils.py
cms/accounts/views.py
cms/accounts/__pycache__/__init__.cpython-35.pyc
cms/accounts/__pycache__/admin.cpython-35.pyc
cms/accounts/__pycache__/apps.cpython-35.pyc
cms/accounts/__pycache__/middleware.cpython-35.pyc
cms/accounts/__pycache__/models.cpython-35.pyc
cms/accounts/__pycache__/serializers.cpython-35.pyc
cms/accounts/__pycache__/social_pipeline.cpython-35.pyc
cms/accounts/__pycache__/urls.cpython-35.pyc
cms/accounts/__pycache__/utils.cpython-35.pyc
cms/accounts/__pycache__/views.cpython-35.pyc
cms/accounts/migrations/0001_initial.py
cms/accounts/migrations/0002_auto_20170103_1346.py
cms/accounts/migrations/__init__.py
cms/accounts/migrations/__pycache__/0001_initial.cpython-35.pyc
cms/accounts/migrations/__pycache__/0002_auto_20170103_1346.cpython-35.pyc
cms/accounts/migrations/__pycache__/__init__.cpython-35.pyc
cms/admin_addons/__init__.py
cms/admin_addons/actions.py
cms/admin_addons/apps.py
cms/admin_addons/dashboard.py
cms/admin_addons/__pycache__/__init__.cpython-35.pyc
cms/admin_addons/__pycache__/actions.cpython-35.pyc
cms/admin_addons/__pycache__/apps.cpython-35.pyc
cms/admin_addons/__pycache__/dashboard.cpython-35.pyc
cms/admin_addons/static/admin/tinymce/config.js
cms/admin_addons/static/admin/tinymce/css/styles.css
cms/admin_addons/static/admin/tinymce/css/styles.css.map
cms/admin_addons/static/admin/tinymce/scss/styles.scss
cms/admin_addons/static/admin/tinymce/scss/bootstrap/_alert.scss
cms/admin_addons/static/admin/tinymce/scss/bootstrap/_animation.scss
cms/admin_addons/static/admin/tinymce/scss/bootstrap/_breadcrumb.scss
cms/admin_addons/static/admin/tinymce/scss/bootstrap/_button-group.scss
cms/admin_addons/static/admin/tinymce/scss/bootstrap/_buttons.scss
pixelcms_server-0.4.2.dist-info/DESCRIPTION.rst
pixelcms_server-0.4.2.dist-info/METADATA
pixelcms_server-0.4.2.dist-info/RECORD
pixelcms_server-0.4.2.dist-info/WHEEL
pixelcms_server-0.4.2.dist-info/metadata.json
pixelcms_server-0.4.2.dist-info/top_level.txt
