Metadata-Version: 2.0
Name: pixelcms-server
Version: 0.4.2
Summary: PixelCMS server part.
Home-page: https://github.com/HurtowniaPixeli/pixelcms-server
Author: Michał Werner
Author-email: michal@hurtowniapixeli.pl
License: MIT
Platform: UNKNOWN
Classifier: Development Status :: 2 - Pre-Alpha
Classifier: Intended Audience :: Developers
Classifier: Environment :: Web Environment
Classifier: Framework :: Django
Classifier: License :: OSI Approved :: MIT License
Classifier: Operating System :: OS Independent
Classifier: Programming Language :: Python
Classifier: Programming Language :: Python :: 3
Classifier: Framework :: Django
Requires-Dist: Django (>=1.10,<1.11)
Requires-Dist: Pillow (<4,>=3.3.1)
Requires-Dist: Pygments (>=2.1.3,<3)
Requires-Dist: Unidecode (>=0.4.19,<1)
Requires-Dist: django-autoslug (>=1.9.4.dev0,<2)
Requires-Dist: django-cors-middleware (>=1.3.1<2)
Requires-Dist: django-cron (>=0.4.6,<1)
Requires-Dist: django-filebrowser (>=3.7.2,<4)
Requires-Dist: django-grappelli (>=2.9.1,<3)
Requires-Dist: django-polymorphic (>=1.0,<2)
Requires-Dist: djangorestframework (<4,>=3.4.6)
Requires-Dist: djangorestframework-camel-case (>=0.2.0,<1)
Requires-Dist: djangorestframework-jwt (>=1.8.0<2)
Requires-Dist: drfdocs (>=0.0.11,<1)
Requires-Dist: psycopg2 (>=2.6.2,<3)
Requires-Dist: requests (>=2.11.1,<3)
Requires-Dist: rest-social-auth (>=1.0.0,<2)
Requires-Dist: social-auth-app-django (>=0.1.0,<0.2)
Requires-Dist: sqlparse (>=0.2.1,<1)
